django_barobill/__init__.py
django_barobill/admin.py
django_barobill/apps.py
django_barobill/choices.py
django_barobill/errors.py
django_barobill/models.py
django_barobill/parsers.py
django_barobill/tests.py
django_barobill/utils.py
django_barobill/views.py
django_barobill/migrations/0001_initial.py
django_barobill/migrations/0002_partner_unique_partner_brn_userid.py
django_barobill/migrations/__init__.py
django_barobill/migrations/__pycache__/0001_initial.cpython-312.pyc
django_barobill/migrations/__pycache__/__init__.cpython-312.pyc
django_barobill-0.1.3.dist-info/LICENSE
django_barobill-0.1.3.dist-info/METADATA
django_barobill-0.1.3.dist-info/WHEEL
django_barobill-0.1.3.dist-info/top_level.txt
django_barobill-0.1.3.dist-info/RECORD
